[
    {
        "AvailabilityZone": "us-west-2a",
        "InstanceType": "c4.8xlarge",
        "ProductDescription": "Linux/UNIX",
        "SpotPrice": "0.531000",
        "Timestamp": "2021-10-18 22:46:24+00:00"
    },
    {
        "AvailabilityZone": "us-west-2a",
        "InstanceType": "c4.8xlarge",
        "ProductDescription": "Linux/UNIX",
        "SpotPrice": "0.534100",
        "Timestamp": "2021-10-18 15:25:16+00:00"
    },
    {
        "AvailabilityZone": "us-west-2a",
        "InstanceType": "c4.8xlarge",
        "ProductDescription": "Linux/UNIX",
        "SpotPrice": "0.529800",
        "Timestamp": "2021-10-18 08:03:42+00:00"
    },
    {
        "AvailabilityZone": "us-west-2a",
        "InstanceType": "c4.8xlarge",
        "ProductDescription": "Linux/UNIX",
        "SpotPrice": "0.528500",
        "Timestamp": "2021-10-18 03:23:25+00:00"
    },
    {
        "AvailabilityZone": "us-west-2a",
        "InstanceType": "c4.8xlarge",
        "ProductDescription": "Linux/UNIX",
        "SpotPrice": "0.525900",
        "Timestamp": "2021-10-17 22:09:06+00:00"
    },
    {
        "AvailabilityZone": "us-west-2a",
        "InstanceType": "c4.8xlarge",
        "ProductDescription": "Linux/UNIX",
        "SpotPrice": "0.516300",
        "Timestamp": "2021-10-24 21:38:48+00:00"
    },
    {
        "AvailabilityZone": "us-west-2a",
        "InstanceType": "c4.8xlarge",
        "ProductDescription": "Linux/UNIX",
        "SpotPrice": "0.514300",
        "Timestamp": "2021-10-24 16:41:48+00:00"
    },
    {
        "AvailabilityZone": "us-west-2a",
        "InstanceType": "c4.8xlarge",
        "ProductDescription": "Linux/UNIX",
        "SpotPrice": "0.515400",
        "Timestamp": "2021-10-24 09:21:07+00:00"
    },
    {
        "AvailabilityZone": "us-west-2a",
        "InstanceType": "c4.8xlarge",
        "ProductDescription": "Linux/UNIX",
        "SpotPrice": "0.514400",
        "Timestamp": "2021-10-24 04:32:01+00:00"
    },
    {
        "AvailabilityZone": "us-west-2a",
        "InstanceType": "c4.8xlarge",
        "ProductDescription": "Linux/UNIX",
        "SpotPrice": "0.513300",
        "Timestamp": "2021-10-23 23:34:59+00:00"
    },
    {
        "AvailabilityZone": "us-west-2a",
        "InstanceType": "c4.8xlarge",
        "ProductDescription": "Linux/UNIX",
        "SpotPrice": "0.513300",
        "Timestamp": "2021-10-23 23:34:59+00:00"
    },
    {
        "AvailabilityZone": "us-west-2a",
        "InstanceType": "c4.8xlarge",
        "ProductDescription": "Linux/UNIX",
        "SpotPrice": "0.514900",
        "Timestamp": "2021-10-23 18:03:58+00:00"
    },
    {
        "AvailabilityZone": "us-west-2a",
        "InstanceType": "c4.8xlarge",
        "ProductDescription": "Linux/UNIX",
        "SpotPrice": "0.518900",
        "Timestamp": "2021-10-23 10:42:40+00:00"
    },
    {
        "AvailabilityZone": "us-west-2a",
        "InstanceType": "c4.8xlarge",
        "ProductDescription": "Linux/UNIX",
        "SpotPrice": "0.519000",
        "Timestamp": "2021-10-23 05:45:49+00:00"
    },
    {
        "AvailabilityZone": "us-west-2a",
        "InstanceType": "c4.8xlarge",
        "ProductDescription": "Linux/UNIX",
        "SpotPrice": "0.521400",
        "Timestamp": "2021-10-22 23:32:01+00:00"
    },
    {
        "AvailabilityZone": "us-west-2a",
        "InstanceType": "c4.8xlarge",
        "ProductDescription": "Linux/UNIX",
        "SpotPrice": "0.521400",
        "Timestamp": "2021-10-22 23:32:01+00:00"
    },
    {
        "AvailabilityZone": "us-west-2a",
        "InstanceType": "c4.8xlarge",
        "ProductDescription": "Linux/UNIX",
        "SpotPrice": "0.522000",
        "Timestamp": "2021-10-22 16:53:44+00:00"
    },
    {
        "AvailabilityZone": "us-west-2a",
        "InstanceType": "c4.8xlarge",
        "ProductDescription": "Linux/UNIX",
        "SpotPrice": "0.519000",
        "Timestamp": "2021-10-22 11:30:28+00:00"
    },
    {
        "AvailabilityZone": "us-west-2a",
        "InstanceType": "c4.8xlarge",
        "ProductDescription": "Linux/UNIX",
        "SpotPrice": "0.519400",
        "Timestamp": "2021-10-22 05:09:05+00:00"
    },
    {
        "AvailabilityZone": "us-west-2a",
        "InstanceType": "c4.8xlarge",
        "ProductDescription": "Linux/UNIX",
        "SpotPrice": "0.520500",
        "Timestamp": "2021-10-21 23:46:42+00:00"
    },
    {
        "AvailabilityZone": "us-west-2a",
        "InstanceType": "c4.8xlarge",
        "ProductDescription": "Linux/UNIX",
        "SpotPrice": "0.520500",
        "Timestamp": "2021-10-21 23:46:42+00:00"
    },
    {
        "AvailabilityZone": "us-west-2a",
        "InstanceType": "c4.8xlarge",
        "ProductDescription": "Linux/UNIX",
        "SpotPrice": "0.520000",
        "Timestamp": "2021-10-21 19:06:04+00:00"
    },
    {
        "AvailabilityZone": "us-west-2a",
        "InstanceType": "c4.8xlarge",
        "ProductDescription": "Linux/UNIX",
        "SpotPrice": "0.519700",
        "Timestamp": "2021-10-21 14:17:42+00:00"
    },
    {
        "AvailabilityZone": "us-west-2a",
        "InstanceType": "c4.8xlarge",
        "ProductDescription": "Linux/UNIX",
        "SpotPrice": "0.521300",
        "Timestamp": "2021-10-21 07:55:54+00:00"
    },
    {
        "AvailabilityZone": "us-west-2a",
        "InstanceType": "c4.8xlarge",
        "ProductDescription": "Linux/UNIX",
        "SpotPrice": "0.523500",
        "Timestamp": "2021-10-21 01:59:23+00:00"
    },
    {
        "AvailabilityZone": "us-west-2a",
        "InstanceType": "c4.8xlarge",
        "ProductDescription": "Linux/UNIX",
        "SpotPrice": "0.523900",
        "Timestamp": "2021-10-20 20:20:20+00:00"
    },
    {
        "AvailabilityZone": "us-west-2a",
        "InstanceType": "c4.8xlarge",
        "ProductDescription": "Linux/UNIX",
        "SpotPrice": "0.523900",
        "Timestamp": "2021-10-20 20:20:20+00:00"
    },
    {
        "AvailabilityZone": "us-west-2a",
        "InstanceType": "c4.8xlarge",
        "ProductDescription": "Linux/UNIX",
        "SpotPrice": "0.527500",
        "Timestamp": "2021-10-20 19:07:16+00:00"
    },
    {
        "AvailabilityZone": "us-west-2a",
        "InstanceType": "c4.8xlarge",
        "ProductDescription": "Linux/UNIX",
        "SpotPrice": "0.527500",
        "Timestamp": "2021-10-20 15:06:19+00:00"
    },
    {
        "AvailabilityZone": "us-west-2a",
        "InstanceType": "c4.8xlarge",
        "ProductDescription": "Linux/UNIX",
        "SpotPrice": "0.525800",
        "Timestamp": "2021-10-20 08:01:48+00:00"
    },
    {
        "AvailabilityZone": "us-west-2a",
        "InstanceType": "c4.8xlarge",
        "ProductDescription": "Linux/UNIX",
        "SpotPrice": "0.526600",
        "Timestamp": "2021-10-20 00:40:13+00:00"
    },
    {
        "AvailabilityZone": "us-west-2a",
        "InstanceType": "c4.8xlarge",
        "ProductDescription": "Linux/UNIX",
        "SpotPrice": "0.530200",
        "Timestamp": "2021-10-19 17:44:44+00:00"
    },
    {
        "AvailabilityZone": "us-west-2a",
        "InstanceType": "c4.8xlarge",
        "ProductDescription": "Linux/UNIX",
        "SpotPrice": "0.530200",
        "Timestamp": "2021-10-19 17:44:44+00:00"
    },
    {
        "AvailabilityZone": "us-west-2a",
        "InstanceType": "c4.8xlarge",
        "ProductDescription": "Linux/UNIX",
        "SpotPrice": "0.532600",
        "Timestamp": "2021-10-19 11:55:45+00:00"
    },
    {
        "AvailabilityZone": "us-west-2a",
        "InstanceType": "c4.8xlarge",
        "ProductDescription": "Linux/UNIX",
        "SpotPrice": "0.531000",
        "Timestamp": "2021-10-18 22:46:24+00:00"
    }
]